pywatchman_unofficial-1.5.0.dist-info/METADATA
pywatchman_unofficial-1.5.0.dist-info/LICENSE
pywatchman_unofficial-1.5.0.dist-info/zip-safe
pywatchman_unofficial-1.5.0.dist-info/top_level.txt
pywatchman_unofficial-1.5.0.dist-info/RECORD
pywatchman_unofficial-1.5.0.dist-info/WHEEL
pywatchman/__init__.py
pywatchman/pybser.py
pywatchman/encoding.py
pywatchman/bser.pypy37-pp73-aarch64-linux-gnu.so
pywatchman/load.py
pywatchman/windows.py
pywatchman/capabilities.py
pywatchman_unofficial-1.5.0.data/scripts/watchman-make
pywatchman_unofficial-1.5.0.data/scripts/watchman-replicate-subscription
pywatchman_unofficial-1.5.0.data/scripts/watchman-wait
