Metadata-Version: 2.1
Name: pywatchman-unofficial
Version: 1.5.0
Summary: Watchman client for python (unofficial)
Home-page: https://github.com/jarshwah/watchman
Author: Wez Furlong, Rain
Author-email: wez@fb.com
Maintainer: Josh Smeaton
Maintainer-email: josh.smeaton@gmail.com
License: BSD
Keywords: watchman inotify fsevents kevent kqueue portfs filesystem watcher
Platform: Platform Independent
Classifier: Development Status :: 5 - Production/Stable
Classifier: Intended Audience :: Developers
Classifier: Topic :: System :: Filesystems
Classifier: License :: OSI Approved :: BSD License
Classifier: Operating System :: OS Independent
Classifier: Programming Language :: Python :: 2
Classifier: Programming Language :: Python :: 2.6
Classifier: Programming Language :: Python :: 2.7
Classifier: Programming Language :: Python :: 3
Classifier: Programming Language :: Python :: 3.5
Classifier: Programming Language :: Python :: 3.6
License-File: LICENSE
